mqtty_cli/__init__.py
mqtty_cli/cli.py
mqtty_cli/config.py
mqtty_cli/logging.py
mqtty_cli/mode/__init__.py
mqtty_cli/mode/exp_multiprocess.py
mqtty_cli/mode/simple.py
mqtty_cli/mode/threaded.py
mqtty_cli/py.typed
mqtty_cli/sync_to_async.py
mqtty_cli/utils.py
ki2_mqtty_cli-1.5.1.dist-info/LICENSE
ki2_mqtty_cli-1.5.1.dist-info/METADATA
ki2_mqtty_cli-1.5.1.dist-info/WHEEL
ki2_mqtty_cli-1.5.1.dist-info/entry_points.txt
ki2_mqtty_cli-1.5.1.dist-info/RECORD
