Metadata-Version: 2.1
Name: ki2-mqtty-cli
Version: 1.5.1
Summary: Command-line utility designed to facilitate the interconnection between serial devices and an MQTT server. This project is based on the `mqtty` library and allows simple configuration using a TOML file.
License: MIT
Author: Adrien KERFOURN
Author-email: ak.sitecontact@gmail.com
Requires-Python: >=3.10,<4.0
Classifier: License :: OSI Approved :: MIT License
Classifier: Programming Language :: Python :: 3
Classifier: Programming Language :: Python :: 3.10
Classifier: Programming Language :: Python :: 3.11
Classifier: Programming Language :: Python :: 3.12
Classifier: Programming Language :: Python :: 3.13
Requires-Dist: aiomqtt (>=2.3.0,<3.0.0)
Requires-Dist: ki2-mqtty (>=1.4.0,<2.0.0)
Requires-Dist: ki2-python-utils (>=0.3.5,<0.4.0)
Requires-Dist: paho-mqtt (>=2.1.0,<3.0.0)
Requires-Dist: pydantic (>=2.10.4,<3.0.0)
Requires-Dist: pyserial (>=3.5,<4.0)
Requires-Dist: tomli (>=2.2.1,<3.0.0)
Requires-Dist: typing-extensions (>=4.12.2,<5.0.0)
